IconMatch/IconMatch.py
IconMatch/__init__.py
IconMatch/box.py
IconMatch/helpers.py
IconMatch/manual_test.py
IconMatch/rectangle.py
IconMatch/weighted_quick_unionUF.py
iconmatch-0.2.0.dist-info/METADATA
iconmatch-0.2.0.dist-info/WHEEL
iconmatch-0.2.0.dist-info/licenses/LICENSE.txt
iconmatch-0.2.0.dist-info/RECORD
