Metadata-Version: 2.3
Name: IconMatch
Version: 0.2.0
Summary: Package for detecting Icons from images or screen
Project-URL: Homepage, https://github.com/NativeSensors/IconMatch
Project-URL: Issues, https://github.com/NativeSensors/IconMatch/Issues
Author-email: Piotr Walas <piotr.walas@eyegestures.com>
Maintainer-email: Piotr Walas <piotr.walas@eyegestures.com>
License: MIT License
License-File: LICENSE.txt
Keywords: Icon,IconMatch,NativeSensors,scanning
Classifier: License :: OSI Approved :: MIT License
Classifier: Operating System :: OS Independent
Classifier: Programming Language :: Python :: 3
Requires-Python: >=3.8
